keycare/RelExtractor.py
keycare/TermExtractor.py
keycare/__init__.py
keycare/categorizers/Categorizer.py
keycare/categorizers/Clustering.py
keycare/categorizers/SetFitClassifier.py
keycare/categorizers/TransformersClassifier.py
keycare/categorizers/__init__.py
keycare/extractors/Extractor.py
keycare/extractors/KeyBertExtractor.py
keycare/extractors/RakeExtractor.py
keycare/extractors/TextRankExtractor.py
keycare/extractors/YakeExtractor.py
keycare/extractors/__init__.py
keycare/relators/Relator.py
keycare/relators/SetFitRelator.py
keycare/relators/TransformersRelator.py
keycare/relators/__init__.py
keycare/tests/termextractor_pipeline.py
keycare/utils/__init__.py
keycare/utils/data_structures.py
keycare-0.1.0.dist-info/licenses/LICENSE
keycare-0.1.0.dist-info/METADATA
keycare-0.1.0.dist-info/WHEEL
keycare-0.1.0.dist-info/top_level.txt
keycare-0.1.0.dist-info/RECORD
