Metadata-Version: 2.4
Name: keycare
Version: 0.1.0
Summary: KeyCARE is a Python library designed for the unsupervised keyword extraction from biomedical documents with the use of different algorithms, the classification of the keywords according to their semantic nature, and the extraction of is a relations among those keywords and with other terminologies.
Author-email: Sergi Marsol <sergimarsolt@gmail.com>
License: MIT License
Project-URL: Homepage, https://github.com/nlp4bia-bsc/KeyCARE
Project-URL: Documentation, https://github.com/nlp4bia-bsc/KeyCARE/docs
Project-URL: Repository, https://github.com/nlp4bia-bsc/KeyCARE
Project-URL: Issues, https://github.com/nlp4bia-bsc/KeyCARE/issues
Classifier: Programming Language :: Python :: 3
Classifier: Operating System :: OS Independent
Requires-Python: >=3.9
License-File: LICENSE
Requires-Dist: datasets==2.14.4
Requires-Dist: evaluate==0.4.0
Requires-Dist: huggingface-hub==0.16.4
Requires-Dist: keybert==0.7.0
Requires-Dist: keyphrase-vectorizers==0.0.11
Requires-Dist: matplotlib==3.7.2
Requires-Dist: nltk==3.8.1
Requires-Dist: numpy==1.25.2
Requires-Dist: pandas==2.0.3
Requires-Dist: pickleshare==0.7.5
Requires-Dist: pytextrank==3.2.5
Requires-Dist: rake-nltk==1.0.6
Requires-Dist: scikit-learn==1.2.2
Requires-Dist: scipy==1.11.1
Requires-Dist: sentence-transformers==2.2.2
Requires-Dist: setfit==0.7.0
Requires-Dist: spacy==3.6.1
Requires-Dist: tokenizers==0.13.3
Requires-Dist: torch==2.0.1
Requires-Dist: transformers==4.33.0
Requires-Dist: yake==0.4.8
Requires-Dist: es-core-news-sm
Dynamic: license-file
